oxmsg/__init__.py
oxmsg/attachment.py
oxmsg/cli.py
oxmsg/message.py
oxmsg/properties.py
oxmsg/py.typed
oxmsg/recipient.py
oxmsg/storage.py
oxmsg/util.py
oxmsg/domain/__init__.py
oxmsg/domain/constants.py
oxmsg/domain/encodings.py
oxmsg/domain/model.py
oxmsg/domain/reference.py
python_oxmsg-0.0.1.dist-info/LICENSE.txt
python_oxmsg-0.0.1.dist-info/METADATA
python_oxmsg-0.0.1.dist-info/WHEEL
python_oxmsg-0.0.1.dist-info/entry_points.txt
python_oxmsg-0.0.1.dist-info/top_level.txt
python_oxmsg-0.0.1.dist-info/RECORD
