Metadata-Version: 2.1
Name: python-oxmsg
Version: 0.0.1
Summary: Extract attachments from Outlook .msg files.
Author-email: Steve Canny <stcanny@gmail.com>
License: MIT
Project-URL: Changelog, https://github.com/scanny/python-oxmsg/blob/master/CHANGELOG.md
Project-URL: Documentation, https://scanny.github.io/python-oxmsg/
Project-URL: Homepage, https://github.com/scanny/python-oxmsg
Project-URL: Repository, https://github.com/scanny/python-oxmsg
Keywords: ms-oxmsg,outlook,email
Classifier: Development Status :: 3 - Alpha
Classifier: Environment :: Console
Classifier: Intended Audience :: Developers
Classifier: License :: OSI Approved :: MIT License
Classifier: Operating System :: OS Independent
Classifier: Programming Language :: Python
Classifier: Programming Language :: Python :: 3
Classifier: Programming Language :: Python :: 3.9
Classifier: Programming Language :: Python :: 3.10
Classifier: Programming Language :: Python :: 3.11
Classifier: Programming Language :: Python :: 3.12
Classifier: Topic :: Communications :: Email
Classifier: Topic :: File Formats
Classifier: Topic :: Office/Business :: Office Suites
Classifier: Topic :: Software Development :: Libraries
Requires-Python: >=3.9
License-File: LICENSE.txt
Requires-Dist: click
Requires-Dist: olefile
Requires-Dist: typing_extensions>=4.9.0
